{"is_source_file": true, "description": "Simple js file", "external_files": [], "external_methods": [], "published": [], "calls": [], "search-terms": [], "classes": [], "methods": [], "state": 2, "file_id": 33, "knowledge_revision": 48, "git_revision": "2af2cc2fa90e24524d5a16f6c63b1adaac0c3b70", "ctags": [], "filename": "tailwind.config.js", "hash": "1740dcfedc2dc7ce615b49ac9ef034d3", "format-version": 4, "code-base-name": "https://github.com/MalaiarasuGRaj/jira-integration.git:main", "revision_history": [{"48": "2af2cc2fa90e24524d5a16f6c63b1adaac0c3b70"}]}